<?xml version="1.0" encoding="utf-8"?>
<app iconPicture = "app/box/resource/icon_dashboard.bin">dashboard
    <script
    file="app/box/box640x360.js">
    </script>
    
 <animateTransform
        type="image frame"
        from="app\\box\\resource\\frame"
        to="app\\box\\resource\\frame"
        dur="5s"
        repeatCount="indefinite">animateFrame
    </animateTransform>
    <animateTransform
        type="opacity"
        values="255;100;255"
        keyTimes="0;0.5;1"
        dur="2s"
        repeatCount="indefinite"
        calcMode="discrete">animateOpacity1
    </animateTransform>
    <animateTransform
        type="opacity"
        values="100;255;100"
        keyTimes="0;0.5;1"
        dur="1s"
        repeatCount="indefinite"
        calcMode="discrete">animateOpacity2
    </animateTransform>
    <animateTransform
        type="opacity"
        values="100;255;100"
        keyTimes="0;0.5;1"
        dur="2s"
        repeatCount="indefinite"
        calcMode="discrete">animateOpacity3
    </animateTransform>
        <animateTransform
        type="opacity"
        values="255;100;100;100;100"
        keyTimes="0;0.2;0.4;0.7;1"
        dur="8s"
        repeatCount="indefinite"
        calcMode="discrete">animateOpacity4
    </animateTransform>
        <animateTransform
        type="opacity"
        values="100;255;100;100;100"
        keyTimes="0;0.2;0.4;0.7;1"
        dur="8s"
        repeatCount="indefinite"
        calcMode="discrete">animateOpacity5
    </animateTransform>
    <animateTransform
        type="opacity"
        values="100;100;255;100;100"
        keyTimes="0;0.2;0.4;0.7;1"
        dur="8s"
        repeatCount="indefinite"
        calcMode="discrete">animateOpacity6
    </animateTransform>
    <animateTransform
        type="opacity"
        values="100;100;100;255;100"
        keyTimes="0;0.2;0.4;0.7;1"
        dur="8s"
        repeatCount="indefinite"
        calcMode="discrete">animateOpacity7
    </animateTransform>
    <animateTransform
        type="translate"
        values="0,0;-284,0;0,0"
        keyTimes="0;0.5;1"
        dur="3s"
        repeatCount="indefinite"
        calcMode="linear"
        >animateMove1
    </animateTransform>
    <animateTransform
        type="opacity"
        values="0;255;0"
        keyTimes="0;0.5;1"
        dur="3s"
        repeatCount="indefinite"
        calcMode="linear"
        >animateOpacity8
    </animateTransform>
     <animateTransform
        type="textContent"
        from="0"
        to="120"
        dur="5s"
        repeatCount="indefinite">animatetextContent1
    </animateTransform>
    <animateTransform
        type="progress"
        from="0"
        to="1"
        dur="5s"
        repeatCount="indefinite">animateProgress1
    </animateTransform>
    <animateTransform
        type="progress"
        from="0"
        to="1"
        dur="7s"
        repeatCount="indefinite">animateProgress2
    </animateTransform>
    <screen
    w="800"
    h="480"
    x="0"
    y="0">screen0
   
<key
            id="51"
            >key1
            <onClick
                    to="multiLevel"
                    type="jump" 
                    id="1,1,ml0">
            </onClick>
    </key>   
<key
            id="50"
            >key2
            <onClick
                    to="multiLevel"
                    type="jump" 
                    id="1,0, ml0   ">
            </onClick>
    </key>  
    <key
            id="49"
            >key3
            <onClick
                    to="multiLevel"
                    type="jump" 
                    id="0,0, ml0">
            </onClick>
    </key>  
<multiLevel>ml0
    <img
        x="0"
        y="0"
        file="app\\box\\resource\\lock_screen_background.bin"
        blendMode="imgBypassMode"
        >lock_screen_background
    </img>
    <textbox
            x="0"
            y="100"
            color="white"
            w="454"
            h="49"
            text="00:00"
            fontSize="100"
            font="app/box/resource/font/Roboto-Bold_size100_bits4_font.bin"
            mode="center">txt_date7
            <onTime
                type="00:00"
                to="txt_date"
                >
            </onTime>
    </textbox>
    <textbox
            x="0"
            y="200"
            color="white"
            w="454"
            h="49"
            text="Mon, Jan 1"
            fontSize="24"
            font="app/box/resource/font/Roboto-Bold_size24_bits4_font.bin"
            mode="center">txt_date8
            <onTime
                type="Mon, Jan 1"
                to="txt_date"
                >
            </onTime>
    </textbox>
    <img
        x="150"
        y="350"
        file="app\\box\\resource\\lock_font_background.bin"
        blendMode="imgSrcOverMode"
        >lock_font_background
    </img>
    <img
        x="294"
        y="365"
        file="app\\box\\resource\\lock_font.bin"
        blendMode="imgSrcOverMode"
        >img_frame2
    </img>
    <seekbar
        x="150"
        y="360"
        w="500"
        h="100"
        opacity="255"
        pictureThumb="app\\box\\resource\\image1-39.bin"
        pictureThumbHighlight="app\\box\\resource\\image1-39-1.bin"
        blendMode="imgSrcOverMode"
        orientation="H"
    
       >bar_brightness
            <onComplete
                    to="multiLevel"
                    type="jump" 
                    id="1,0">
            </onComplete>
    </seekbar>

    <multiLevel>ml10
       <img
        x="0"
        y="0"
        file="app\\box\\resource\\speed_main_background.bin"
        blendMode="imgBypassMode"
        >speed_main_background
    </img>
    <img
        x="10"
        y="100"
        file="app\\box\\resource\\speed_turn_left3.bin"
        blendMode="imgSrcOverMode"
        >speed_turn_left3
        <onLoad
            to="speed_turn_left3"
            type="animate" 
            id="animateOpacity1">
        </onLoad>
    </img>
    <img
        x="80"
        y="130"
        file="app\\box\\resource\\speed_turn_left2.bin"
        blendMode="imgSrcOverMode"
        >speed_turn_left2
        <onLoad
            to="speed_turn_left2"
            type="animate" 
            id="animateOpacity1">
        </onLoad>
    </img>
    <img
        x="150"
        y="160"
        file="app\\box\\resource\\speed_turn_left1.bin"
        blendMode="imgSrcOverMode"
        >speed_turn_left1
        <onLoad
            to="speed_turn_left1"
            type="animate" 
            id="animateOpacity1">
        </onLoad>
    </img>
    <img
        x="650"
        y="100"
        file="app\\box\\resource\\speed_turn_right3.bin"
        blendMode="imgSrcOverMode"
        >speed_turn_right3
        <onLoad
            to="speed_turn_right3"
            type="animate" 
            id="animateOpacity3">
        </onLoad>
    </img>
    <img
        x="600"
        y="130"
        file="app\\box\\resource\\speed_turn_right2.bin"
        blendMode="imgSrcOverMode"
        >speed_turn_right2
        <onLoad
            to="speed_turn_right2"
            type="animate" 
            id="animateOpacity3">
        </onLoad>
    </img>
    <img
        x="550"
        y="160"
        file="app\\box\\resource\\speed_turn_right1.bin"
        blendMode="imgSrcOverMode"
        >speed_turn_right1
        <onLoad
            to="speed_turn_right1"
            type="animate" 
            id="animateOpacity3">
        </onLoad>
    </img>

<seekbar
            x="202"
             y="53"
            w="399"
            h="399"
            opacity="255"
            folder="app\\box\\resource\\frame"
            blendMode="imgFilterBlack"
            orientation="arc"
            centralX="200"
            centralY="200"
            startDegree="200"
            endDegree="160">speed_arc
            <onChange
            type="write"
            to="txt_speed">
       </onChange>    
       <onLoad
            to="speed_arc"
            type="animate" 
            id="animateProgress1">
        </onLoad>
</seekbar>


    <img
        x="202"
        y="53"
        file="app\\box\\resource\\speed_background.bin"
        blendMode="imgSrcOverMode"
        >speed_background
    </img>
    <img
        x="202"
        y="53"
        file="app\\box\\resource\\speed_stroke.bin"
        blendMode="imgSrcOverMode"
        >speed_stroke
    </img>
        <img
        x="253"
        y="435"
        file="app\\box\\resource\\bottom.bin"
        blendMode="imgSrcOverMode"
        >bottom
    </img>
    <img
        x="320"
        y="440"
        file="app\\box\\resource\\R_icon.bin"
        blendMode="imgSrcOverMode"
        >R_icon
        <onLoad
            to="R_icon"
            type="animate" 
            id="animateOpacity4">
        </onLoad>
    </img>
<img
        x="370"
        y="440"
        file="app\\box\\resource\\P_icon.bin"
        blendMode="imgSrcOverMode"
        >P_icon
        <onLoad
            to="P_icon"
            type="animate" 
            id="animateOpacity5">
        </onLoad>
    </img>
    <img
        x="420"
        y="440"
        file="app\\box\\resource\\N_icon.bin"
        blendMode="imgSrcOverMode"
        >N_icon
        <onLoad
            to="N_icon"
            type="animate" 
            id="animateOpacity6">
        </onLoad>
    </img>
    <img
        x="470"
        y="440"
        file="app\\box\\resource\\D_icon.bin"
        blendMode="imgSrcOverMode"
        >D_icon
        <onLoad
            to="D_icon"
            type="animate" 
            id="animateOpacity7">
        </onLoad>
    </img>


    
    <img
        x="204"
        y="53"
        file="app\\box\\resource\\speed_dial.bin"
        blendMode="imgSrcOverMode"
        >speed_dial
    </img>
    <img
        x="347"
        y="150"
        file="app\\box\\resource\\main_ready.bin"
        blendMode="imgSrcOverMode"
        >main_ready
    </img>
    <textbox
            x="202"
            y="180"
            color="white"
            w="395"
            h="100"
            text="00"
            fontSize="100"
            font="app/box/resource/font/Roboto-Bold_size100_bits4_font.bin"
            mode="center">txt_speed
        </textbox>
    <textbox
            x="202"
            y="320"
            color="white"
            w="395"
            h="100"
            text="km/h"
            fontSize="24"
            font="app/box/resource/font/Roboto-Bold_size24_bits4_font.bin"
            mode="center">txt_kmh
        </textbox>   

         <textbox
            x="100"
            y="400"
            color="white"
            w="454"
            h="49"
            text="00:00"
            fontSize="24"
            font="app/box/resource/font/Roboto-Bold_size24_bits4_font.bin"
            mode="left">txt_date7
            <onTime
                type="00:00"
                to="txt_date"
                >
            </onTime>
    </textbox> 
        <img
        x="600"
        y="410"
        file="app\\box\\resource\\main_TPIP.bin"
        blendMode="imgSrcOverMode"
        >main_TPIP
    </img>
<textbox
            x="660"
            y="408"
            color="white"
            w="395"
            h="100"
            text="100km"
            fontSize="24"
            font="app/box/resource/font/Roboto-Bold_size24_bits4_font.bin"
            mode="left">txt_currentValuemark
        </textbox>  
<img
        x="600"
        y="443"
        file="app\\box\\resource\\main_ODO.bin"
        blendMode="imgSrcOverMode"
        >main_ODO
    </img>
    <img
        x="790"
        y="200"
        file="app\\box\\resource\\main_module_back1.bin"
        blendMode="imgSrcOverMode"
        >main_module_back1
        <onLoad
            to="main_module_back1"
            type="animate" 
            id="animateMove1">
        </onLoad>
        <onLoad
            to="main_module_back1"
            type="animate" 
            id="animateOpacity8">
        </onLoad>
    </img>
<textbox
            x="660"
            y="440"
            color="white"
            w="395"
            h="100"
            text="2000km"
            fontSize="24"
            font="app/box/resource/font/Roboto-Bold_size24_bits4_font.bin"
            mode="left">txt_currentValuemark
        </textbox>   

    <img
        x="100"
        y="10"
        file="app\\box\\resource\\main_turn_left.bin"
        blendMode="imgSrcOverMode"
        >main_turn_left
        <onLoad
            to="main_turn_left"
            type="animate" 
            id="animateOpacity1">
        </onLoad>
    </img>
    <img
        x="300"
        y="10"
        file="app\\box\\resource\\main_depped_light.bin"
        blendMode="imgSrcOverMode"
        >main_depped_light
        <onLoad
            to="main_depped_light"
            type="animate" 
            id="animateOpacity2">
        </onLoad>
    </img>
    <img
        x="500"
        y="10"
        file="app\\box\\resource\\main_location.bin"
        blendMode="imgSrcOverMode"
        >main_location
        <onLoad
            to="main_location"
            type="animate" 
            id="animateOpacity1">
        </onLoad>
    </img>
    <img
        x="700"
        y="10"
        file="app\\box\\resource\\main_signal.bin"
        blendMode="imgSrcOverMode"
        >main_signal
        <onLoad
            to="main_signal"
            type="animate" 
            id="animateOpacity2">
        </onLoad>
    </img>
   <img
        x="30"
        y="440"
        file="app\\box\\resource\\soc_background.bin"
        blendMode="imgSrcOverMode"
        >soc_background
</img>
<seekbar
        x="33"
        y="442"
        w="57"
        h="19"
        opacity="255"
        picture="app\\box\\resource\\soc_icon.bin"
        blendMode="imgSrcOverMode"
        orientation="H"
    
       >soc_icon
       <onChange
            type="write"
            to="txt_currentsoc">
       </onChange>    
       <onLoad
            to="soc_icon"
            type="animate" 
            id="animateProgress1">
        </onLoad>
    </seekbar>




       <img
        x="56"
        y="443"
        file="app\\box\\resource\\soc_charge.bin"
        blendMode="imgSrcOverMode"
        >soc_charge
    </img>
<textbox
            x="100"
            y="440"
            color="white"
            w="48"
            h="100"
            text="20"
            fontSize="24"
            font="app/box/resource/font/Roboto-Bold_size24_bits4_font.bin"
            mode="right">txt_currentsoc
        </textbox>  
        <textbox
            x="148"
            y="440"
            color="white"
            w="395"
            h="100"
            text="%"
            fontSize="24"
            font="app/box/resource/font/Roboto-Bold_size24_bits4_font.bin"
            mode="left">txt_currentsocper
        </textbox>  
    </multiLevel>
    <multiLevel>ml11
       
        <img
        x="0"
        y="0"
        file="app\\box\\resource\\speed_main_background.bin"
        blendMode="imgBypassMode"
        >speed_main_background
    </img>
    <img
        x="100"
        y="10"
        file="app\\box\\resource\\main_turn_left.bin"
        blendMode="imgSrcOverMode"
        >main_turn_left
        <onLoad
            to="main_turn_left"
            type="animate" 
            id="animateOpacity1">
        </onLoad>
    </img>
    <img
        x="300"
        y="10"
        file="app\\box\\resource\\main_depped_light.bin"
        blendMode="imgSrcOverMode"
        >main_depped_light
        <onLoad
            to="main_depped_light"
            type="animate" 
            id="animateOpacity2">
        </onLoad>
    </img>
    <img
        x="500"
        y="10"
        file="app\\box\\resource\\main_location.bin"
        blendMode="imgSrcOverMode"
        >main_location
        <onLoad
            to="main_location"
            type="animate" 
            id="animateOpacity1">
        </onLoad>
    </img>
    <img
        x="700"
        y="10"
        file="app\\box\\resource\\main_signal.bin"
        blendMode="imgSrcOverMode"
        >main_signal
        <onLoad
            to="main_signal"
            type="animate" 
            id="animateOpacity2">
        </onLoad>
    </img>
   <img
        x="30"
        y="440"
        file="app\\box\\resource\\soc_background.bin"
        blendMode="imgSrcOverMode"
        >soc_background
</img>
<seekbar
        x="33"
        y="442"
        w="57"
        h="19"
        opacity="255"
        picture="app\\box\\resource\\soc_icon.bin"
        blendMode="imgSrcOverMode"
        orientation="H"
    
       >soc_icon
       <onChange
            type="write"
            to="txt_currentsoc">
       </onChange>   
       <onLoad
            to="soc_icon"
            type="animate" 
            id="animateProgress1">
        </onLoad> 
    </seekbar>




       <img
        x="56"
        y="443"
        file="app\\box\\resource\\soc_charge.bin"
        blendMode="imgSrcOverMode"
        >soc_charge
    </img>
<textbox
            x="100"
            y="440"
            color="white"
            w="48"
            h="100"
            text="20"
            fontSize="24"
            font="app/box/resource/font/Roboto-Bold_size24_bits4_font.bin"
            mode="right">txt_currentsoc
        </textbox>  
        <textbox
            x="148"
            y="440"
            color="white"
            w="395"
            h="100"
            text="%"
            fontSize="24"
            font="app/box/resource/font/Roboto-Bold_size24_bits4_font.bin"
            mode="left">txt_currentsocper
        </textbox>  
        <img
        x="600"
        y="410"
        file="app\\box\\resource\\main_TPIP.bin"
        blendMode="imgSrcOverMode"
        >main_TPIP
    </img>
<textbox
            x="660"
            y="408"
            color="white"
            w="395"
            h="100"
            text="100km"
            fontSize="24"
            font="app/box/resource/font/Roboto-Bold_size24_bits4_font.bin"
            mode="left">txt_currentValuemark
        </textbox>  
<img
        x="600"
        y="443"
        file="app\\box\\resource\\main_ODO.bin"
        blendMode="imgSrcOverMode"
        >main_ODO
    </img>
    <textbox
            x="660"
            y="440"
            color="white"
            w="395"
            h="100"
            text="2000km"
            fontSize="24"
            font="app/box/resource/font/Roboto-Bold_size24_bits4_font.bin"
            mode="left">txt_currentValuemark
        </textbox>   
        <textbox
            x="75"
            y="180"
            color="white"
            w="150"
            h="100"
            text="00"
            fontSize="100"
            font="app/box/resource/font/Roboto-Bold_size100_bits4_font.bin"
            mode="center">txt_speed_main
            <onLoad
            to="txt_speed_main"
            type="animate" 
            id="animatetextContent1">
            </onLoad>
        </textbox>
            <textbox
            x="130"
            y="320"
            color="white"
            w="50"
            h="100"
            text="km/h"
            fontSize="24"
            font="app/box/resource/font/Roboto-Bold_size24_bits4_font.bin"
            mode="right">txt_kmh
        </textbox>  
        <img
        x="247"
        y="360"
        file="app\\box\\resource\\main_ready.bin"
        blendMode="imgSrcOverMode"
        >main_ready
        <onLoad
            to="main_ready"
            type="animate" 
            id="animateOpacity2">
        </onLoad>
        </img>
         <img
        x="300"
        y="80"
        file="app\\box\\resource\\main_arrows.bin"
        blendMode="imgSrcOverMode"
        >main_arrows
        </img>
    <radio
        picture="app\\box\\resource\\rect11.bin"
        highlightPicture="app\\box\\resource\\image1-53.bin"
        blendMode="imgSrcOverMode"
        opacity="255"
        pictureX="0"
        pictureY="0"
        rotationAngle="0"
        w="100"
        h="80"
        x="700"
        y="60"
        name="main_radio">main_radio1
          <onSelect 
                    to="tabview"
                    type="jump" 
                    id="0,0,tv1">
            </onSelect >
</radio>  
    <radio
        picture="app\\box\\resource\\rect1-6.bin"
        highlightPicture="app\\box\\resource\\image1-53-0.bin"
        blendMode="imgSrcOverMode"
        opacity="255"
        pictureX="0"
        pictureY="0"
        rotationAngle="0"
        w="100"
        h="80"
        x="700"
        y="140"
        name="main_radio">main_radio1
        <onSelect 
                    to="tabview"
                    type="jump" 
                    id="1,0,tv1">
            </onSelect >
        
</radio>
    <radio
        picture="app\\box\\resource\\rect1-9.bin"
        highlightPicture="app\\box\\resource\\image1-53-9.bin"
        blendMode="imgSrcOverMode"
        opacity="255"
        pictureX="0"
        pictureY="0"

        w="100"
        h="80"
        x="700"
        y="220"
        name="main_radio">main_radio2
         <onSelect 
                    to="tabview"
                    type="jump" 
                    id="2,0,tv1">
            </onSelect >       
</radio>

  <radio
        picture="app\\box\\resource\\rect1-0.bin"
        highlightPicture="app\\box\\resource\\image1-53-4.bin"
        blendMode="imgSrcOverMode"
        opacity="255"
        pictureX="0"
        pictureY="0"

        w="100"
        h="80"
        x="700"
        y="300"
        name="main_radio">main_radio3
         <onSelect 
                    to="tabview"
                    type="jump" 
                    id="3,0,tv1">
            </onSelect >       
</radio>
<tabview gestures="false">tv1
			<tab >t1
				<textbox
            x="400"
            y="140"
            color="white"
            w="300"
            h="100"
            text="bright"
            fontSize="24"
            font="app/box/resource/font/Roboto-Bold_size24_bits4_font.bin"
            mode="left">bright
        </textbox>   
			</tab>
			<tab idx="1">t2
				<textbox
            x="400"
            y="140"
            color="white"
            w="300"
            h="100"
            text="turn right"
            fontSize="24"
            font="app/box/resource/font/Roboto-Bold_size24_bits4_font.bin"
            mode="left">turn
        </textbox>
        <img
        x="500"
        y="140"
        file="app\\box\\resource\\icon_arrow_2.bin"
        blendMode="imgSrcOverMode"
        >icon_arrow_2
       
        </img>
			</tab>
			<tab idx="2">t2
				<textbox
            x="400"
            y="140"
            color="white"
            w="300"
            h="100"
            text="phone book"
            fontSize="24"
            font="app/box/resource/font/Roboto-Bold_size24_bits4_font.bin"
            mode="left">turn
        </textbox>
			</tab>
			<tab idx="3">t2
				<textbox
            x="400"
            y="140"
            color="white"
            w="300"
            h="100"
            text="music name"
            fontSize="24"
            font="app/box/resource/font/Roboto-Bold_size24_bits4_font.bin"
            mode="left">turn
        </textbox>
         <img
        x="500"
        y="140"
        file="app\\box\\resource\\main_music_icon.bin"
        blendMode="main_music_icon"
        >main_music_icon
       
        </img>
			</tab>
		</tabview>		
    </multiLevel>
</multiLevel>


    </screen>

</app>
